Laboratorio002/src/Sumador4bits/Sumador.v
module sum1b (a,b,ci,s,co);
input a;
input b;
input ci;

output s;
output co;

wire X1; // salida de compuerta XOR 1
wire A1; // salida de compuerta AND 1
wire A2; // salida de compuerta AND 2

//Conexión de compuertas
assign X1 = a ^ b; 
assign A1 = a & b;
assign A2 = X1 & ci;
assign s = X1 ^ ci;
assign co = A1 | A2;

endmodule

Laboratorio002/src/Sumador4bits/Sumador4.v
`include "Sumador.v"

module sum4b(A, B, Ci, S, Co);

input [3:0] A;
input [3:0] B;
input Ci;
output [3:0] S;   
output Co;

wire C1,C2,C3;

sum1b sum0(.a(A[0]), .b(B[0]), .ci(Ci),.s(S[0]), .co(C1));
sum1b sum1(.a(A[1]), .b(B[1]), .ci(C1), .s(S[1]), .co(C2));
sum1b sum2(.a(A[2]), .b(B[2]), .ci(C2), .s(S[2]), .co(C3));
sum1b sum3(.a(A[3]), .b(B[3]), .ci(C3), .s(S[3]), .co(Co));

endmodule

Laboratorio002/src/Sumador4bits/Sumador4_tb.v
`include "Sumador4.v"
`timescale 1ps/1ps

module Sumador4_tb ();

    reg [3:0] A_tb;
    reg [3:0] B_tb;
    reg Ci_tb;

    sum4b uut(
        .A(A_tb),
        .B(B_tb),
        .Ci(Ci_tb)
    );

    initial begin
        A_tb = 4'b0000;
        B_tb = 4'b0000;
        Ci_tb = 0;
        #1;
        A_tb = 4'b0001;
        B_tb = 4'b0001;
        Ci_tb = 0;
        #1;
        A_tb = 4'b0010;
        B_tb = 4'b0010;
        Ci_tb = 0;
        #1;
        A_tb = 4'b0011;
        B_tb = 4'b0011;
        Ci_tb = 0;
        #1;
        A_tb = 4'b0100;
        B_tb = 4'b0100;
        Ci_tb = 0;
        #1;
        A_tb = 4'b0101;
        B_tb = 4'b0101;
        Ci_tb = 0;
        #1;
        A_tb = 4'b0110;
        B_tb = 4'b0110;
        Ci_tb = 0;
        #1;
        A_tb = 4'b0111;
        B_tb = 4'b0111;
        Ci_tb = 0;
        #1;
        A_tb = 4'b1000;
        B_tb = 4'b1000;
        Ci_tb = 0;
        #1;
        A_tb = 4'b1001;
        B_tb = 4'b1001;
        Ci_tb = 0;
        #1;
        A_tb = 4'b1010;
        B_tb = 4'b1010;
        Ci_tb = 0;
        #1;
        A_tb = 4'b1011;
        B_tb = 4'b1011;
        Ci_tb = 0;
        #1;
        A_tb = 4'b1100;
        B_tb = 4'b1100;
        Ci_tb = 0;
        #1;
        A_tb = 4'b1101;
        B_tb = 4'b1101;
        Ci_tb = 0;
        #1;
        A_tb = 4'b1110;
        B_tb = 4'b1110;
        Ci_tb = 0;
        #1;
        A_tb = 4'b1111;
        B_tb = 4'b1111;
        Ci_tb = 0;
        #1;
    end

    initial begin: TEST_CASE
      $dumpfile("Sumador4_tb.vcd");
      $dumpvars(-1,uut);
      #18; 
      $finish;
    end

endmodule

Laboratorio002/src/Sumador4bits/build/Sumador4_tb.vcd
$date
	Mon Apr  1 09:54:23 2024
$end
$version
	Icarus Verilog
$end
$timescale
	1ps
$end
$scope module Sumador4_tb $end
$scope module uut $end
$var wire 4 ! A [3:0] $end
$var wire 4 " B [3:0] $end
$var wire 1 # Ci $end
$var wire 4 $ S [3:0] $end
$var wire 1 % Co $end
$var wire 1 & C3 $end
$var wire 1 ' C2 $end
$var wire 1 ( C1 $end
$scope module sum0 $end
$var wire 1 ) A1 $end
$var wire 1 * A2 $end
$var wire 1 + X1 $end
$var wire 1 , a $end
$var wire 1 - b $end
$var wire 1 # ci $end
$var wire 1 ( co $end
$var wire 1 . s $end
$upscope $end
$scope module sum1 $end
$var wire 1 / A1 $end
$var wire 1 0 A2 $end
$var wire 1 1 X1 $end
$var wire 1 2 a $end
$var wire 1 3 b $end
$var wire 1 ( ci $end
$var wire 1 ' co $end
$var wire 1 4 s $end
$upscope $end
$scope module sum2 $end
$var wire 1 5 A1 $end
$var wire 1 6 A2 $end
$var wire 1 7 X1 $end
$var wire 1 8 a $end
$var wire 1 9 b $end
$var wire 1 ' ci $end
$var wire 1 & co $end
$var wire 1 : s $end
$upscope $end
$scope module sum3 $end
$var wire 1 ; A1 $end
$var wire 1 < A2 $end
$var wire 1 = X1 $end
$var wire 1 > a $end
$var wire 1 ? b $end
$var wire 1 & ci $end
$var wire 1 % co $end
$var wire 1 @ s $end
$upscope $end
$upscope $end
$upscope $end
$enddefinitions $end
#0
$dumpvars
0@
0?
0>
0=
0<
0;
0:
09
08
07
06
05
04
03
02
01
00
0/
0.
0-
0,
0+
0*
0)
0(
0'
0&
0%
b0 $
0#
b0 "
b0 !
$end
#1
b10 $
14
1(
1)
1-
1,
b1 "
b1 !
#2
04
b100 $
1:
0(
1'
0)
1/
0-
13
0,
12
b10 "
b10 !
#3
b110 $
14
1(
1)
1-
1,
b11 "
b11 !
#4
04
0:
b1000 $
1@
0(
0'
1&
0)
0/
15
0-
03
19
0,
02
18
b100 "
b100 !
#5
b1010 $
14
1(
1)
1-
1,
b101 "
b101 !
#6
04
b1100 $
1:
0(
1'
0)
1/
0-
13
0,
12
b110 "
b110 !
#7
b1110 $
14
1(
1)
1-
1,
b111 "
b111 !
#8
04
0:
b0 $
0@
0(
0'
0&
1%
0)
0/
05
1;
0-
03
09
1?
0,
02
08
1>
b1000 "
b1000 !
#9
b10 $
14
1(
1)
1-
1,
b1001 "
b1001 !
#10
04
b100 $
1:
0(
1'
0)
1/
0-
13
0,
12
b1010 "
b1010 !
#11
b110 $
14
1(
1)
1-
1,
b1011 "
b1011 !
#12
04
0:
b1000 $
1@
0(
0'
1&
0)
0/
15
0-
03
19
0,
02
18
b1100 "
b1100 !
#13
b1010 $
14
1(
1)
1-
1,
b1101 "
b1101 !
#14
04
b1100 $
1:
0(
1'
0)
1/
0-
13
0,
12
b1110 "
b1110 !
#15
b1110 $
14
1(
1)
1-
1,
b1111 "
b1111 !
