Laboratorio003/src/Parte2/seg7.v
module seg7 (BCD, SSeg, an);

  input [3:0] BCD;
  output reg [0:6] SSeg;
  output [3:0] an;
  
  assign an = 4'b1110;


always @ ( * ) begin
  case (BCD)

                   // abcdefg
   4'b0000: SSeg = 7'b0000001; // "0"  
	 4'b0001: SSeg = 7'b1001111; // "1" 
	 4'b0010: SSeg = 7'b0010010; // "2" 
	 4'b0011: SSeg = 7'b0000110; // "3" 
	 4'b0100: SSeg = 7'b1001100; // "4" 
	 4'b0101: SSeg = 7'b0100100; // "5" 
	 4'b0110: SSeg = 7'b0100000; // "6" 
	 4'b0111: SSeg = 7'b0001111; // "7" 
	 4'b1000: SSeg = 7'b0000000; // "8"  
	 4'b1001: SSeg = 7'b0000100; // "9" 
	 4'ha: SSeg = 7'b0001000;  
	 4'hb: SSeg = 7'b1100000;
   4'hc: SSeg = 7'b0110001;
   4'hd: SSeg = 7'b1000010;
   4'he: SSeg = 7'b0110000;
   4'hf: SSeg = 7'b0111000;
    default:
    SSeg = 0;
  endcase
end

endmodule

Laboratorio003/src/Parte2/Sumador1bit.v
module lab01 (A,B,CI,S1,CO);
input A;
input B;
input CI;

output S1;
output CO;

wire X1; // salida de compuerta XOR 1
wire A1; // salida de compuerta AND 1
wire A2; // salida de compuerta AND 2

//Conexión de compuertas
assign X1 = A ^ B; 
assign A1 = A & B;
assign A2 = X1 & CI;
assign S1 = X1 ^ CI;
assign CO = A1 | A2;

endmodule

Laboratorio003/src/Parte2/lab03.v
`include "Sumador1bit.v"

module lab03(A, B, CI, S, CO);
  input [2:0] A, B;
  input CI;
  output [2:0] S;
  output CO;

  wire [1:0] C; // Acarreos internos

  // Sumadores de 1 bit
  lab01 sum1bit0 (.A(A[0]), .B(B[0]), .CI(CI), .S1(S[0]), .CO(C[0]));
  lab01 sum1bit1 (.A(A[1]), .B(B[1]), .CI(C[0]), .S1(S[1]), .CO(C[1]));
  lab01 sum1bit2 (.A(A[2]), .B(B[2]), .CI(C[1]), .S1(S[2]), .CO(CO));
endmodule

Laboratorio003/src/Parte2/sumwdisplay.v
module sumwdisplay(
  input [2:0] A, B,
  input CI,
  output [3:0] S_CO, // Salida concatenada de S y CO
  output [2:0] S,
  output CO,
  output [3:0] an,
  output reg [0:6] SSeg
);

  wire [1:0] C; // Acarreos internos

  // Concatenamos CO con S para formar S_CO
  assign S_CO = {CO, S};

  // Sumador de 3 bits
  lab03 uut(
    .A(A),
    .B(B),
    .CI(CI),
    .S(S),
    .CO(CO)
  );

  // Conexión al display de 7 segmentos
  seg7 display(
    .BCD(S_CO), // Conectamos la salida del sumador (S) al BCD del display
    .SSeg(SSeg), // Conectamos las salidas del display de 7 segmentos
    .an(an) // Conectamos la salida del display de 7 segmentos a los ánodos
  );

endmodule

Laboratorio003/src/Parte2/sumwdisplay_tb.v
`include "sumwdisplay.v"
`timescale 1ps/1ps

module sumwdisplay_tb ();

  reg [2:0] A_tb; // Entradas de 3 bits
  reg [2:0] B_tb;
  reg CI_tb;
  wire [2:0] S_tb; // Salidas de 3 bits
  wire CO_tb;
  wire [3:0] S_CO;// Salida concatenada de S y CO
  wire [6:0] SSeg_tb;

  sumwdisplay uut(
    .A(A_tb),
    .B(B_tb),
    .CI(CI_tb),
    .S(S_tb),
    .CO(CO_tb),
    .SSeg(SSeg_tb)
  );
  
   // Instancia del sumador de 3 bits

  initial begin
  A_tb = 3'b000;
  B_tb = 3'b000;
  CI_tb = 0;
  #100;
  A_tb = 3'b001;
  B_tb = 3'b001;
  CI_tb = 0;
  #100;
  A_tb = 3'b010;
  B_tb = 3'b010;
  CI_tb = 0;
  #100;
  A_tb = 3'b011;
  B_tb = 3'b011;
  CI_tb = 0;
  #100;
  A_tb = 3'b100;
  B_tb = 3'b100;
  CI_tb = 0;
  #100;
  A_tb = 3'b101;
  B_tb = 3'b101;
  CI_tb = 0;
  #100;
  A_tb = 3'b110;
  B_tb = 3'b110;
  CI_tb = 0;
  #100;
  A_tb = 3'b111;
  B_tb = 3'b111;
  CI_tb = 0;
  #100;
  end


  initial begin: TEST_CASE
    $dumpfile("sumwdisplay_tb.vcd");
    $dumpvars(-1,uut);
    #800; 
    $finish;
end

endmodule

Laboratorio003/src/Parte2/build/sumwdisplay_tb.vcd
$date
	Sat Apr 06 18:51:02 2024
$end
$version
	Icarus Verilog
$end
$timescale
	1ps
$end
$scope module sumwdisplay_tb $end
$scope module uut $end
$var wire 3 ! A [2:0] $end
$var wire 3 " B [2:0] $end
$var wire 1 # CI $end
$var wire 4 $ an [3:0] $end
$var wire 4 % S_CO [3:0] $end
$var wire 7 & SSeg [0:6] $end
$var wire 3 ' S [2:0] $end
$var wire 1 ( CO $end
$scope module display $end
$var wire 4 ) BCD [3:0] $end
$var wire 4 * an [3:0] $end
$var reg 7 + SSeg [0:6] $end
$upscope $end
$scope module uut $end
$var wire 3 , A [2:0] $end
$var wire 3 - B [2:0] $end
$var wire 1 # CI $end
$var wire 3 . S [2:0] $end
$var wire 1 ( CO $end
$var wire 2 / C [1:0] $end
$scope module sum1bit0 $end
$var wire 1 0 A $end
$var wire 1 1 A1 $end
$var wire 1 2 A2 $end
$var wire 1 3 B $end
$var wire 1 # CI $end
$var wire 1 4 CO $end
$var wire 1 5 S1 $end
$var wire 1 6 X1 $end
$upscope $end
$scope module sum1bit1 $end
$var wire 1 7 A $end
$var wire 1 8 A1 $end
$var wire 1 9 A2 $end
$var wire 1 : B $end
$var wire 1 ; CI $end
$var wire 1 < CO $end
$var wire 1 = S1 $end
$var wire 1 > X1 $end
$upscope $end
$scope module sum1bit2 $end
$var wire 1 ? A $end
$var wire 1 @ A1 $end
$var wire 1 A A2 $end
$var wire 1 B B $end
$var wire 1 C CI $end
$var wire 1 ( CO $end
$var wire 1 D S1 $end
$var wire 1 E X1 $end
$upscope $end
$upscope $end
$upscope $end
$upscope $end
$enddefinitions $end
#0
$dumpvars
0E
0D
0C
0B
0A
0@
0?
0>
0=
0<
0;
0:
09
08
07
06
05
04
03
02
01
00
b0 /
b0 .
b0 -
b0 ,
b1 +
b1110 *
b0 )
0(
b0 '
b1 &
b0 %
b1110 $
0#
b0 "
b0 !
$end
#100
b10010 &
b10010 +
b10 %
b10 )
b10 '
b10 .
1=
1;
b1 /
14
11
13
10
b1 "
b1 -
b1 !
b1 ,
#200
b1001100 &
b1001100 +
0=
b100 %
b100 )
b100 '
b100 .
1D
0;
1C
04
b10 /
1<
01
18
03
1:
00
17
b10 "
b10 -
b10 !
b10 ,
#300
b100000 &
b100000 +
b110 %
b110 )
b110 '
b110 .
1=
1;
b11 /
14
11
13
10
b11 "
b11 -
b11 !
b11 ,
#400
0=
b0 '
b0 .
0D
0;
0C
b0 &
b0 +
04
b0 /
0<
b1000 %
b1000 )
1(
01
08
1@
03
0:
1B
00
07
1?
b100 "
b100 -
b100 !
b100 ,
#500
b1000 &
b1000 +
b1010 %
b1010 )
b10 '
b10 .
1=
1;
b1 /
14
11
13
10
b101 "
b101 -
b101 !
b101 ,
#600
b110001 &
b110001 +
0=
b1100 %
b1100 )
b100 '
b100 .
1D
0;
1C
04
b10 /
1<
01
18
03
1:
00
17
b110 "
b110 -
b110 !
b110 ,
#700
b110000 &
b110000 +
b1110 %
b1110 )
b110 '
b110 .
1=
1;
b11 /
14
11
13
10
b111 "
b111 -
b111 !
b111 ,
