Laboratorio003/src/Parte1/seg7.v
module seg7 (BCD, SSeg, an);

  input [3:0] BCD;
  output reg [0:6] SSeg;
  output [3:0] an;
  
  assign an = 4'b1110;


always @ ( * ) begin
  case (BCD)

                         // abcdefg
         4'b0000: SSeg = 7'b0000001; // "0"  
	 4'b0001: SSeg = 7'b1001111; // "1" 
	 4'b0010: SSeg = 7'b0010010; // "2" 
	 4'b0011: SSeg = 7'b0000110; // "3" 
	 4'b0100: SSeg = 7'b1001100; // "4" 
	 4'b0101: SSeg = 7'b0100100; // "5" 
	 4'b0110: SSeg = 7'b0100000; // "6" 
	 4'b0111: SSeg = 7'b0001111; // "7" 
	 4'b1000: SSeg = 7'b0000000; // "8"  
	 4'b1001: SSeg = 7'b0000100; // "9" 
    default:
    SSeg = 0;
  endcase
end

endmodule

Laboratorio003/src/Parte1/seg7_tb.v
`include "seg7.v"
`timescale 1ps/1ps

module seg7_tb ();

   reg [3:0] BCD_tb;
   wire [6:0] SSeg_tb;

   seg7 uut(
      .BCD(BCD_tb),
      .SSeg(SSeg_tb)
   );

   initial begin
   BCD_tb = 4'b0000;
   #100;
   BCD_tb = 4'b0001;
   #100;
   BCD_tb = 4'b0010;
   #100;
   BCD_tb = 4'b0011;
   #100;
   BCD_tb = 4'b0100;
   #100;
   BCD_tb = 4'b0101;
   #100;
   BCD_tb = 4'b0110;
   #100;
   BCD_tb = 4'b0111;
   #100;
   BCD_tb = 4'b1000;
   #100;
   BCD_tb = 4'b1001;
   #100;
   end

   initial begin: TEST_CASE
      $dumpfile("seg7_tb.vcd");
      $dumpvars(-1,uut);
      #1000; 
      $finish;
  end
endmodule

Laboratorio003/src/Parte1/build/seg7_tb.vcd
$date
	Sat Apr 06 19:31:32 2024
$end
$version
	Icarus Verilog
$end
$timescale
	1ps
$end
$scope module seg7_tb $end
$scope module uut $end
$var wire 4 ! BCD [3:0] $end
$var wire 4 " an [3:0] $end
$var reg 7 # SSeg [0:6] $end
$upscope $end
$upscope $end
$enddefinitions $end
#0
$dumpvars
b1 #
b1110 "
b0 !
$end
#100
b1001111 #
b1 !
#200
b10010 #
b10 !
#300
b110 #
b11 !
#400
b1001100 #
b100 !
#500
b100100 #
b101 !
#600
b100000 #
b110 !
#700
b1111 #
b111 !
#800
b0 #
b1000 !
#900
b100 #
b1001 !
